{
    "taxes": {
        "info": "Sizin ölkədən getmək hüququnuz məhdudlaşdırılmayıb."
    },
    "infocenter": [
        {
            "ad_soyad_ata_adi": "QULİYEVA LEYLA AZAD",
            "daire_ve_unvani": "25 saylı Nizami ikinci seçki dairəsi\nÜnvan: NİZAMİ RAYONU, BƏHRUZ NURİYEV 21A",
            "dairenin_marsrutu": "",
            "mentqenin_unvani": "14 saylı məntəqə\nUnvan: NİZAMİ R., BƏHRUZ NURİYEV KÜÇ., 69, 251 №-Lİ TAM ORTA MƏKTƏB",
            "mentqenin_marsrutu": "0",
            "secicinin_unvani": "NAXÇIVANSKİ KÜÇ, ev 60, 40"
        }
    ],
    "emlak": {
        "Ad": "LEYLA",
        "Soyad": "QULİYEVA",
        "Ata Adı": "AZAD QIZI",
        "Doğum Tarihi": "2003-09-10",
        "Qeydiyyat Ünvanı": "BAKI ŞƏHƏRİ, SURAXANI RAYONU, ZIĞ QƏSƏBƏSİ, , SURAXANI-HÖVSAN YOLU,ƏSAS KÜÇƏ,4-CÜ DÖNGƏ,EV 1",
        "ŞV Seriyası ve Numarası": "AA1467090",
        "FİN Kod": "79PCNXB"
    },
    "aile_terkibi": [
        {
            "dairenin_kodu": "25",
            "mentqenin_kodu": "14",
            "secicinin_soyadi_adi": "QULİYEV AZAD MƏHYƏDDİN",
            "yasayis_yeri": "NAXÇIVANSKİ KÜÇ, ev 60",
            "tevellud": "1976"
        },
        {
            "dairenin_kodu": "25",
            "mentqenin_kodu": "14",
            "secicinin_soyadi_adi": "QULİYEV KAMRAN VİDADİ",
            "yasayis_yeri": "NAXÇIVANSKİ KÜÇ, ev 60",
            "tevellud": "1991"
        },
        {
            "dairenin_kodu": "25",
            "mentqenin_kodu": "14",
            "secicinin_soyadi_adi": "QULİYEV MURAD MƏHYƏDDİN",
            "yasayis_yeri": "NAXÇIVANSKİ KÜÇ, ev 60",
            "tevellud": "1981"
        },
        {
            "dairenin_kodu": "25",
            "mentqenin_kodu": "14",
            "secicinin_soyadi_adi": "QULİYEVA AĞABACI XƏLİFƏ",
            "yasayis_yeri": "NAXÇIVANSKİ KÜÇ, ev 60",
            "tevellud": "1981"
        },
        {
            "dairenin_kodu": "25",
            "mentqenin_kodu": "14",
            "secicinin_soyadi_adi": "QULİYEVA ALMAZ HƏSRƏT",
            "yasayis_yeri": "NAXÇIVANSKİ KÜÇ, ev 60",
            "tevellud": "1962"
        },
        {
            "dairenin_kodu": "25",
            "mentqenin_kodu": "14",
            "secicinin_soyadi_adi": "QULİYEVA ƏNTİQƏ RƏHİM",
            "yasayis_yeri": "NAXÇIVANSKİ KÜÇ, ev 60",
            "tevellud": "1954"
        },
        {
            "dairenin_kodu": "25",
            "mentqenin_kodu": "14",
            "secicinin_soyadi_adi": "QULİYEVA LEYLA AZAD",
            "yasayis_yeri": "NAXÇIVANSKİ KÜÇ, ev 60",
            "tevellud": "2003"
        }
    ],
    "mehkeme_result": "Qeydiyyatda olan məhkəmə işi tapılmamışdır.",
    "cinayet_result": "Cinayət tərkib məkhəməsi yoxdur",
    "inzibati_result": "Inzibati tərkib məkhəməsi yoxdur"
}